autodistill_transformers/__init__.py
autodistill_transformers/transformers_model.py
autodistill_transformers-0.1.1.dist-info/LICENSE
autodistill_transformers-0.1.1.dist-info/METADATA
autodistill_transformers-0.1.1.dist-info/WHEEL
autodistill_transformers-0.1.1.dist-info/top_level.txt
autodistill_transformers-0.1.1.dist-info/RECORD
