Metadata-Version: 2.1
Name: autodistill-transformers
Version: 0.1.1
Summary: Use object detection models in Hugging Face Transformers to automatically label data to train a fine-tuned model.
Home-page: https://github.com/autodistill/autodistill-transformers
Author: Roboflow
Author-email: support@roboflow.com
Classifier: Programming Language :: Python :: 3
Classifier: License :: OSI Approved :: MIT License
Classifier: Operating System :: OS Independent
Requires-Python: >=3.7
License-File: LICENSE
Requires-Dist: autodistill
Requires-Dist: transformers
Requires-Dist: supervision
Requires-Dist: Pillow
Requires-Dist: torch
Provides-Extra: dev
Requires-Dist: flake8 ; extra == 'dev'
Requires-Dist: black ==22.3.0 ; extra == 'dev'
Requires-Dist: isort ; extra == 'dev'
Requires-Dist: twine ; extra == 'dev'
Requires-Dist: pytest ; extra == 'dev'
Requires-Dist: wheel ; extra == 'dev'
